edx_organizations-7.3.0.dist-info/licenses/LICENSE
organizations/__init__.py
organizations/admin.py
organizations/api.py
organizations/data.py
organizations/exceptions.py
organizations/models.py
organizations/permissions.py
organizations/resources.py
organizations/serializers.py
organizations/urls.py
organizations/validators.py
organizations/management/__init__.py
organizations/management/commands/__init__.py
organizations/management/commands/add_organization.py
organizations/management/commands/tests/__init__.py
organizations/management/commands/tests/test_add_organization.py
organizations/migrations/0001_initial.py
organizations/migrations/0001_squashed_0007_historicalorganization.py
organizations/migrations/0002_auto_20170117_1434.py
organizations/migrations/0002_unique_short_name.py
organizations/migrations/0003_auto_20170221_1138.py
organizations/migrations/0003_historicalorganizationcourse.py
organizations/migrations/0004_auto_20170413_2315.py
organizations/migrations/0004_auto_20230727_2054.py
organizations/migrations/0005_auto_20171116_0640.py
organizations/migrations/0006_auto_20171207_0259.py
organizations/migrations/0007_historicalorganization.py
organizations/migrations/__init__.py
organizations/tests/__init__.py
organizations/tests/factories.py
organizations/tests/test_admin.py
organizations/tests/test_api.py
organizations/tests/test_data.py
organizations/tests/test_migrations.py
organizations/tests/test_models.py
organizations/tests/test_serializers.py
organizations/tests/utils.py
organizations/v0/__init__.py
organizations/v0/urls.py
organizations/v0/views.py
organizations/v0/tests/__init__.py
organizations/v0/tests/test_views.py
edx_organizations-7.3.0.dist-info/METADATA
edx_organizations-7.3.0.dist-info/WHEEL
edx_organizations-7.3.0.dist-info/top_level.txt
edx_organizations-7.3.0.dist-info/RECORD
