Metadata-Version: 2.4
Name: edx-organizations
Version: 7.3.0
Summary: Organization management module for Open edX
Home-page: https://github.com/openedx/edx-organizations
Author: edX
License: AGPL
Classifier: Development Status :: 5 - Production/Stable
Classifier: Environment :: Web Environment
Classifier: Framework :: Django
Classifier: Framework :: Django :: 4.2
Classifier: Intended Audience :: Developers
Classifier: License :: OSI Approved :: GNU Affero General Public License v3
Classifier: Operating System :: OS Independent
Classifier: Programming Language :: Python
Classifier: Programming Language :: Python :: 3
Classifier: Programming Language :: Python :: 3.11
Classifier: Programming Language :: Python :: 3.12
License-File: LICENSE
Requires-Dist: Pillow
Requires-Dist: django
Requires-Dist: django-model-utils
Requires-Dist: django-simple-history>=3.10.1
Requires-Dist: djangorestframework
Requires-Dist: edx-drf-extensions
Requires-Dist: edx-opaque-keys>=0.1.2
Requires-Dist: setuptools
Dynamic: author
Dynamic: classifier
Dynamic: description
Dynamic: home-page
Dynamic: license
Dynamic: license-file
Dynamic: requires-dist
Dynamic: summary
